dataRead.cp37-win_amd64.pyd
mdfconverter/Ui_mdfreaderui4.py
mdfconverter/Ui_mdfreaderui5.py
mdfconverter/__init__.py
mdfconverter/mdfconverter.py
mdfconverter/mdfreaderui4.py
mdfconverter/mdfreaderui5.py
mdfreader/__init__.py
mdfreader/__main__.py
mdfreader/channel.py
mdfreader/mdf.py
mdfreader/mdf3reader.py
mdfreader/mdf4reader.py
mdfreader/mdfinfo3.py
mdfreader/mdfinfo4.py
mdfreader/mdfreader.py
mdfreader-4.1.dist-info/COPYING
mdfreader-4.1.dist-info/LICENSE
mdfreader-4.1.dist-info/METADATA
mdfreader-4.1.dist-info/WHEEL
mdfreader-4.1.dist-info/entry_points.txt
mdfreader-4.1.dist-info/top_level.txt
mdfreader-4.1.dist-info/RECORD
