Metadata-Version: 2.1
Name: mdfreader
Version: 4.1
Summary: A Measured Data Format file parser
Home-page: https://github.com/ratal/mdfreader
Author: Aymeric Rateau
Author-email: aymeric.rateau@gmail.com
License: GPL3
Requires-Dist: numpy (>=1.14)
Requires-Dist: sympy
Requires-Dist: lxml
Provides-Extra: compression
Requires-Dist: blosc ; extra == 'compression'
Provides-Extra: converter
Requires-Dist: PyQt5 ; extra == 'converter'
Provides-Extra: experimental
Requires-Dist: bitarray ; extra == 'experimental'
Provides-Extra: export
Requires-Dist: hdf5storage ; extra == 'export'
Requires-Dist: h5py ; extra == 'export'
Requires-Dist: scipy ; extra == 'export'
Requires-Dist: xlwt ; extra == 'export'
Requires-Dist: xlwt3 ; extra == 'export'
Requires-Dist: openpyxl (>2.0) ; extra == 'export'
Requires-Dist: pandas ; extra == 'export'
Requires-Dist: fastparquet ; extra == 'export'
Provides-Extra: plot
Requires-Dist: matplotlib ; extra == 'plot'
Requires-Dist: mpldatacursor ; extra == 'plot'
